modcfg/__init__.py
modcfg/components.py
modcfg/errors.py
modcfg/grammar.lark
modcfg/lark_components.py
modcfg/parser.py
modcfg/utils.py
modcfg-0.1.3.dist-info/LICENSE.txt
modcfg-0.1.3.dist-info/WHEEL
modcfg-0.1.3.dist-info/METADATA
modcfg-0.1.3.dist-info/RECORD
