Metadata-Version: 2.1
Name: modcfg
Version: 0.1.3
Summary: Yes, another config lang
Home-page: https://github.com/ThatXliner/modcfg
License: GPL-3.0-or-later
Author: Bryan Hu
Author-email: bryan.hu.2020@gmail.com
Requires-Python: >=3.7,<4.0
Classifier: Development Status :: 4 - Beta
Classifier: License :: OSI Approved :: GNU General Public License v3 or later (GPLv3+)
Classifier: Operating System :: OS Independent
Classifier: Programming Language :: Python :: 3
Classifier: Programming Language :: Python :: 3.7
Classifier: Programming Language :: Python :: 3.8
Classifier: Programming Language :: Python :: 3.9
Classifier: Programming Language :: Python :: Implementation :: CPython
Classifier: Topic :: Software Development :: Compilers
Classifier: Typing :: Typed
Requires-Dist: lark-parser (>=0.11.2,<0.12.0)
Project-URL: Bug Tracker, https://github.com/ThatXliner/modcfg/issues
Project-URL: Documentation, https://modcfg.readthedocs.io/en/latest/
Project-URL: Repository, https://github.com/ThatXliner/modcfg
